extendedjsonschema/__init__.py
extendedjsonschema/errors.py
extendedjsonschema/keyword.py
extendedjsonschema/optimizer.py
extendedjsonschema/program.py
extendedjsonschema/schema.py
extendedjsonschema/tools.py
extendedjsonschema/utils.py
extendedjsonschema/validator.py
extended_jsonschema-0.1.0.dist-info/LICENSE
extended_jsonschema-0.1.0.dist-info/METADATA
extended_jsonschema-0.1.0.dist-info/WHEEL
extended_jsonschema-0.1.0.dist-info/top_level.txt
extended_jsonschema-0.1.0.dist-info/RECORD
